__init__.py
DataBase/AbstractDataSaverManager.py
DataBase/HDF5NewDaemon.py
DataBase/MySQLNewDaemon.py
DataBase/__init__.py
ExternalModules/AbstractExternal.py
ExternalModules/__init__.py
ExternalModules/ExternalLib/SabrCalibration.py
ExternalModules/ExternalLib/TestDash.py
ExternalModules/ExternalLib/__init__.py
HDF_storage/dev_validate_record.py
HDF_storage_24Jul/dev_validate_record.py
InstrumentManager/AbstractInstrument.py
InstrumentManager/InstrumentManager.py
InstrumentManager/__init__.py
InstrumentManager/testAbstractInstrument.py
OrderManager/OrderManager.py
OrderManager/__init__.py
Scrapper/ScrapperWithPreSelectedMaturities.py
Scrapper/TradingInterface.py
Scrapper/__init__.py
ScriptPipelines/DownloadEthSurface.py
ScriptPipelines/VisualizeCalibration.py
Strategy/AbstractStrategy.py
Strategy/BasicStrategy.py
Strategy/EmptyStrategy.py
Strategy/__init__.py
Subsciption/AbstractSubscription.py
Subsciption/NullSubscription.py
Subsciption/OrderBookSubscriptionLimitedDepth.py
Subsciption/OwnOrderUpdate.py
Subsciption/TradesSubscription.py
Subsciption/UserPortfolioChanges.py
Subsciption/__init__.py
SyncLib/AvailableRequests.py
SyncLib/CreateOptionSurface.py
SyncLib/DeribitConnectionOld.py
SyncLib/DownloadOptionWithIndexPrice.py
SyncLib/Scrapper.py
Utils/AvailableConfigurationRoot.py
Utils/AvailableCurrencies.py
Utils/AvailableInstrumentType.py
Utils/AvailableInstruments.py
Utils/CircularBuffer.py
Utils/MSG_LIST.py
Utils/OrderStructure.py
Utils/TickerNode.py
Utils/__init__.py
Utils/mysqlRecording/cleanUpRequestsLimited.py
Utils/mysqlRecording/cleanUpRequestsUnlimited.py
Utils/mysqlRecording/postDataTemplateLimited.py
deribit_scrapper-0.0.109.dist-info/LICENSE.txt
deribit_scrapper-0.0.109.dist-info/METADATA
deribit_scrapper-0.0.109.dist-info/WHEEL
deribit_scrapper-0.0.109.dist-info/top_level.txt
deribit_scrapper-0.0.109.dist-info/RECORD
